MANIFEST.in
setup.cfg
setup.py
tw/__init__.py
tw.uitheme.egg-info/PKG-INFO
tw.uitheme.egg-info/SOURCES.txt
tw.uitheme.egg-info/dependency_links.txt
tw.uitheme.egg-info/entry_points.txt
tw.uitheme.egg-info/namespace_packages.txt
tw.uitheme.egg-info/not-zip-safe
tw.uitheme.egg-info/paster_plugins.txt
tw.uitheme.egg-info/requires.txt
tw.uitheme.egg-info/top_level.txt
tw/uitheme/__init__.py
tw/uitheme/release.py
tw/uitheme/static/black-tie/jquery-ui-1.8.9.custom.css
tw/uitheme/static/black-tie/images/ui-bg_diagonals-thick_8_333333_40x40.png
tw/uitheme/static/black-tie/images/ui-bg_flat_65_ffffff_40x100.png
tw/uitheme/static/black-tie/images/ui-bg_glass_40_111111_1x400.png
tw/uitheme/static/black-tie/images/ui-bg_glass_55_1c1c1c_1x400.png
tw/uitheme/static/black-tie/images/ui-bg_highlight-hard_100_f9f9f9_1x100.png
tw/uitheme/static/black-tie/images/ui-bg_highlight-hard_40_aaaaaa_1x100.png
tw/uitheme/static/black-tie/images/ui-bg_highlight-soft_50_aaaaaa_1x100.png
tw/uitheme/static/black-tie/images/ui-bg_inset-hard_45_cd0a0a_1x100.png
tw/uitheme/static/black-tie/images/ui-bg_inset-hard_55_ffeb80_1x100.png
tw/uitheme/static/black-tie/images/ui-icons_222222_256x240.png
tw/uitheme/static/black-tie/images/ui-icons_4ca300_256x240.png
tw/uitheme/static/black-tie/images/ui-icons_bbbbbb_256x240.png
tw/uitheme/static/black-tie/images/ui-icons_ededed_256x240.png
tw/uitheme/static/black-tie/images/ui-icons_ffcf29_256x240.png
tw/uitheme/static/black-tie/images/ui-icons_ffffff_256x240.png
tw/uitheme/static/blitzer/jquery-ui-1.8.9.custom.css
tw/uitheme/static/blitzer/images/ui-bg_diagonals-thick_75_f3d8d8_40x40.png
tw/uitheme/static/blitzer/images/ui-bg_dots-small_65_a6a6a6_2x2.png
tw/uitheme/static/blitzer/images/ui-bg_flat_0_333333_40x100.png
tw/uitheme/static/blitzer/images/ui-bg_flat_65_ffffff_40x100.png
tw/uitheme/static/blitzer/images/ui-bg_flat_75_ffffff_40x100.png
tw/uitheme/static/blitzer/images/ui-bg_glass_55_fbf8ee_1x400.png
tw/uitheme/static/blitzer/images/ui-bg_highlight-hard_100_eeeeee_1x100.png
tw/uitheme/static/blitzer/images/ui-bg_highlight-hard_100_f6f6f6_1x100.png
tw/uitheme/static/blitzer/images/ui-bg_highlight-soft_15_cc0000_1x100.png
tw/uitheme/static/blitzer/images/ui-icons_004276_256x240.png
tw/uitheme/static/blitzer/images/ui-icons_cc0000_256x240.png
