Metadata-Version: 1.0
Name: tw.uitheme
Version: 0.2.2
Summary: theming for jquery plugins packaged as tosca widgets ressources, based on 1.8.9
Home-page: http://jqueryui.com/themeroller/
Author: Nicolas Laurance
Author-email: nicolas[dot]laurance[at]gmail[dot]com
License: UNKNOWN
Keywords: toscawidgets.widgets,css,jquery,theme
Platform: UNKNOWN
Classifier: Development Status :: 5 - Production/Stable
Classifier: Environment :: Web Environment
Classifier: Environment :: Web Environment :: ToscaWidgets
Classifier: Topic :: Software Development :: Libraries :: Python Modules
Classifier: Topic :: Software Development :: Widget Sets
Classifier: Intended Audience :: Developers
Classifier: Operating System :: OS Independent
Classifier: Programming Language :: Python
